lccpy/__init__.py
lccpy/asymongo/__init__.py
lccpy/asymongo/_core.py
lccpy/asymongo/Dependent Packages/motor/LICENSE
lccpy/asymysql/__init__.py
lccpy/asymysql/_core.py
lccpy/asymysql/Dependent Packages/aiomysql/LICENSE
lccpy/coolapi/__init__.py
lccpy/coolapi/_core.py
lccpy/coolapi/Dependent Packages/tornado/LICENSE
lccpy/coolfunc/__init__.py
lccpy/coolfunc/_coolfunc.py
lccpy/coolmongo/__init__.py
lccpy/coolmongo/_core.py
lccpy/coolmongo/Dependent Packages/pymongo/LICENSE
lccpy/cooltime/__init__.py
lccpy/cooltime/_core.py
lccpy/encrypt256/__init__.py
lccpy/encrypt256/_core.py
lccpy/encrypt256/Dependent Packages/pycryptodome/LICENSE
lccpy/increment/__init__.py
lccpy/increment/_core.py
lccpy/rstyleslice/__init__.py
lccpy/rstyleslice/_rstyleslice.py
lccpy/vtype/__init__.py
lccpy/vtype/_vtype.py
lccpy-1.5.dist-info/LICENSE
lccpy-1.5.dist-info/WHEEL
lccpy-1.5.dist-info/METADATA
lccpy-1.5.dist-info/RECORD
