Metadata-Version: 2.1
Name: lccpy
Version: 1.5
Summary: 项目 <让Python更简单一点> 的依赖包
Author-email: "lcctoor.com" <lcctoor@outlook.com>
Requires-Python: >=3.7
Classifier: License :: OSI Approved :: Apache Software License
Requires-Dist: motor
Requires-Dist: aiomysql
Requires-Dist: pymongo
Requires-Dist: pycryptodome
Requires-Dist: tornado
Project-URL: HomePage, https://github.com/lcctoor/lccpy#readme
